<root>
	<item code="donator_name" source='database' column='C_CITIZEN_NAME'>
		<!--<thong_tin_toa_do>-->
	</item>
	
	<item code="donator_address" source='database' column='xml/txtName'>
		<!--<thong_tin_toa_do>-->
	</item>
	
	<item code="amount_number" source='database' column="C_RETURN_PHONE_NUMBER">
		<!--<thong_tin_toa_do>-->
	</item>
	
	<item code="amount_text" source='database' column="C_RETURN_PHONE_NUMBER">
		<!--<thong_tin_toa_do>-->
	</item>
	
	<item code="date" source='date'>
		<!--<thong_tin_toa_do>-->
	</item>
</root>